{"type": "FeatureCollection", "features": [{"geometry": {"type": "Point", "coordinates": [-113.166483, 33.937516]}, "type": "Feature", "id": "Aguila", "properties": {"fips": "0400730"}}, {"geometry": {"type": "Point", "coordinates": [-112.883874, 32.392279]}, "type": "Feature", "id": "Ajo", "properties": {"fips": "0400870"}}, {"geometry": {"type": "Point", "coordinates": [-112.009078, 32.287326]}, "type": "Feature", "id": "Ak Chin", "properties": {"fips": "0400940"}}, {"geometry": {"type": "Point", "coordinates": [-112.08079, 33.019628]}, "type": "Feature", "id": "Ak-Chin Village", "properties": {"fips": "0401090"}}, {"geometry": {"type": "Point", "coordinates": [-113.500316, 34.255853]}, "type": "Feature", "id": "Alamo Lake", "properties": {"fips": "0401170"}}, {"geometry": {"type": "Point", "coordinates": [-112.558394, 31.816919]}, "type": "Feature", "id": "Ali Chuk", "properties": {"fips": "0401560"}}, {"geometry": {"type": "Point", "coordinates": [-111.801625, 31.911528]}, "type": "Feature", "id": "Ali Chukson", "properties": {"fips": "0401570"}}, {"geometry": {"type": "Point", "coordinates": [-111.780387, 31.902547]}, "type": "Feature", "id": "Ali Molina", "properties": {"fips": "0401620"}}, {"geometry": {"type": "Point", "coordinates": [-109.143719, 33.845509]}, "type": "Feature", "id": "Alpine", "properties": {"fips": "0401920"}}, {"geometry": {"type": "Point", "coordinates": [-111.060803, 31.697358]}, "type": "Feature", "id": "Amado", "properties": {"fips": "0401990"}}, {"geometry": {"type": "Point", "coordinates": [-112.034963, 32.374193]}, "type": "Feature", "id": "Anegam", "properties": {"fips": "0402270"}}, {"geometry": {"type": "Point", "coordinates": [-113.808288, 35.422991]}, "type": "Feature", "id": "Antares", "properties": {"fips": "0402410"}}, {"geometry": {"type": "Point", "coordinates": [-112.12314, 33.849663]}, "type": "Feature", "id": "Anthem", "properties": {"fips": "0402430"}}, {"geometry": {"type": "Point", "coordinates": [-111.535346, 33.398314]}, "type": "Feature", "id": "Apache Junction", "properties": {"fips": "0402830"}}, {"geometry": {"type": "Point", "coordinates": [-111.292612, 31.574939]}, "type": "Feature", "id": "Arivaca", "properties": {"fips": "0403320"}}, {"geometry": {"type": "Point", "coordinates": [-111.07377, 31.738973]}, "type": "Feature", "id": "Arivaca Junction", "properties": {"fips": "0403380"}}, {"geometry": {"type": "Point", "coordinates": [-111.670454, 32.750787]}, "type": "Feature", "id": "Arizona City", "properties": {"fips": "0403530"}}, {"geometry": {"type": "Point", "coordinates": [-114.589339, 34.854836]}, "type": "Feature", "id": "Arizona Village", "properties": {"fips": "0403915"}}, {"geometry": {"type": "Point", "coordinates": [-112.774601, 33.334994]}, "type": "Feature", "id": "Arlington", "properties": {"fips": "0404020"}}, {"geometry": {"type": "Point", "coordinates": [-112.491303, 35.217188]}, "type": "Feature", "id": "Ash Fork", "properties": {"fips": "0404440"}}, {"geometry": {"type": "Point", "coordinates": [-114.660049, 32.719042]}, "type": "Feature", "id": "Avenue B and C", "properties": {"fips": "0404710"}}, {"geometry": {"type": "Point", "coordinates": [-112.329077, 33.313041]}, "type": "Feature", "id": "Avondale", "properties": {"fips": "0404720"}}, {"geometry": {"type": "Point", "coordinates": [-111.339266, 32.419517]}, "type": "Feature", "id": "Avra Valley", "properties": {"fips": "0404880"}}, {"geometry": {"type": "Point", "coordinates": [-113.44271, 32.808134]}, "type": "Feature", "id": "Aztec", "properties": {"fips": "0404930"}}, {"geometry": {"type": "Point", "coordinates": [-113.177008, 34.577109]}, "type": "Feature", "id": "Bagdad", "properties": {"fips": "0405140"}}, {"geometry": {"type": "Point", "coordinates": [-111.067383, 34.292399]}, "type": "Feature", "id": "Bear Flat", "properties": {"fips": "0405450"}}, {"geometry": {"type": "Point", "coordinates": [-113.938597, 36.907305]}, "type": "Feature", "id": "Beaver Dam", "properties": {"fips": "0405490"}}, {"geometry": {"type": "Point", "coordinates": [-111.300023, 34.342985]}, "type": "Feature", "id": "Beaver Valley", "properties": {"fips": "0405495"}}, {"geometry": {"type": "Point", "coordinates": [-110.328552, 31.914497]}, "type": "Feature", "id": "Benson", "properties": {"fips": "0405770"}}, {"geometry": {"type": "Point", "coordinates": [-110.874919, 31.392024]}, "type": "Feature", "id": "Beyerville", "properties": {"fips": "0405970"}}, {"geometry": {"type": "Point", "coordinates": [-109.931834, 31.398036]}, "type": "Feature", "id": "Bisbee", "properties": {"fips": "0406260"}}, {"geometry": {"type": "Point", "coordinates": [-111.647495, 36.61177]}, "type": "Feature", "id": "Bitter Springs", "properties": {"fips": "0406470"}}, {"geometry": {"type": "Point", "coordinates": [-112.122024, 34.070945]}, "type": "Feature", "id": "Black Canyon City", "properties": {"fips": "0406610"}}, {"geometry": {"type": "Point", "coordinates": [-111.586969, 33.050357]}, "type": "Feature", "id": "Blackwater", "properties": {"fips": "0406820"}}, {"geometry": {"type": "Point", "coordinates": [-114.262886, 34.170415]}, "type": "Feature", "id": "Bluewater", "properties": {"fips": "0407025"}}, {"geometry": {"type": "Point", "coordinates": [-113.996245, 33.898438]}, "type": "Feature", "id": "Bouse", "properties": {"fips": "0407310"}}, {"geometry": {"type": "Point", "coordinates": [-109.484454, 32.324831]}, "type": "Feature", "id": "Bowie", "properties": {"fips": "0407380"}}, {"geometry": {"type": "Point", "coordinates": [-113.937883, 33.672082]}, "type": "Feature", "id": "Brenda", "properties": {"fips": "0407590"}}, {"geometry": {"type": "Point", "coordinates": [-109.823078, 32.925827]}, "type": "Feature", "id": "Bryce", "properties": {"fips": "0407915"}}, {"geometry": {"type": "Point", "coordinates": [-112.647138, 33.430118]}, "type": "Feature", "id": "Buckeye", "properties": {"fips": "0407940"}}, {"geometry": {"type": "Point", "coordinates": [-114.483064, 32.740349]}, "type": "Feature", "id": "Buckshot", "properties": {"fips": "0408020"}}, {"geometry": {"type": "Point", "coordinates": [-114.561149, 35.129773]}, "type": "Feature", "id": "Bullhead City", "properties": {"fips": "0408220"}}, {"geometry": {"type": "Point", "coordinates": [-109.624792, 35.75336]}, "type": "Feature", "id": "Burnside", "properties": {"fips": "0408535"}}, {"geometry": {"type": "Point", "coordinates": [-110.114922, 33.127656]}, "type": "Feature", "id": "Bylas", "properties": {"fips": "0408710"}}, {"geometry": {"type": "Point", "coordinates": [-109.721246, 32.76047]}, "type": "Feature", "id": "Cactus Flats", "properties": {"fips": "0408920"}}, {"geometry": {"type": "Point", "coordinates": [-111.316922, 32.957823]}, "type": "Feature", "id": "Cactus Forest", "properties": {"fips": "0408990"}}, {"geometry": {"type": "Point", "coordinates": [-111.428716, 35.852962]}, "type": "Feature", "id": "Cameron", "properties": {"fips": "0409340"}}, {"geometry": {"type": "Point", "coordinates": [-110.69843, 32.562885]}, "type": "Feature", "id": "Campo Bonito", "properties": {"fips": "0409580"}}, {"geometry": {"type": "Point", "coordinates": [-111.857014, 34.569405]}, "type": "Feature", "id": "Camp Verde", "properties": {"fips": "0409690"}}, {"geometry": {"type": "Point", "coordinates": [-112.911788, 36.934154]}, "type": "Feature", "id": "Cane Beds", "properties": {"fips": "0409900"}}, {"geometry": {"type": "Point", "coordinates": [-110.039913, 33.783921]}, "type": "Feature", "id": "Canyon Day", "properties": {"fips": "0410040"}}, {"geometry": {"type": "Point", "coordinates": [-111.914146, 33.823073]}, "type": "Feature", "id": "Carefree", "properties": {"fips": "0410180"}}, {"geometry": {"type": "Point", "coordinates": [-110.331096, 33.979354]}, "type": "Feature", "id": "Carrizo", "properties": {"fips": "0410320"}}, {"geometry": {"type": "Point", "coordinates": [-111.908087, 33.115452]}, "type": "Feature", "id": "Casa Blanca", "properties": {"fips": "0410460"}}, {"geometry": {"type": "Point", "coordinates": [-111.762121, 32.907111]}, "type": "Feature", "id": "Casa Grande", "properties": {"fips": "0410530"}}, {"geometry": {"type": "Point", "coordinates": [-111.010526, 32.34171]}, "type": "Feature", "id": "Casas Adobes", "properties": {"fips": "0410670"}}, {"geometry": {"type": "Point", "coordinates": [-110.899635, 32.484898]}, "type": "Feature", "id": "Catalina", "properties": {"fips": "0411160"}}, {"geometry": {"type": "Point", "coordinates": [-110.884843, 32.301872]}, "type": "Feature", "id": "Catalina Foothills", "properties": {"fips": "0411230"}}, {"geometry": {"type": "Point", "coordinates": [-111.982191, 33.836205]}, "type": "Feature", "id": "Cave Creek", "properties": {"fips": "0411300"}}, {"geometry": {"type": "Point", "coordinates": [-110.195707, 33.891399]}, "type": "Feature", "id": "Cedar Creek", "properties": {"fips": "0411370"}}, {"geometry": {"type": "Point", "coordinates": [-112.981325, 36.953807]}, "type": "Feature", "id": "Centennial Park", "properties": {"fips": "0411500"}}, {"geometry": {"type": "Point", "coordinates": [-109.791341, 32.868055]}, "type": "Feature", "id": "Central", "properties": {"fips": "0411580"}}, {"geometry": {"type": "Point", "coordinates": [-110.815386, 33.400078]}, "type": "Feature", "id": "Central Heights-Midland City", "properties": {"fips": "0411720"}}, {"geometry": {"type": "Point", "coordinates": [-111.854943, 33.282874]}, "type": "Feature", "id": "Chandler", "properties": {"fips": "0412000"}}, {"geometry": {"type": "Point", "coordinates": [-112.600116, 32.247321]}, "type": "Feature", "id": "Charco", "properties": {"fips": "0412150"}}, {"geometry": {"type": "Point", "coordinates": [-111.776473, 31.940954]}, "type": "Feature", "id": "Chiawuli Tak", "properties": {"fips": "0412560"}}, {"geometry": {"type": "Point", "coordinates": [-110.049831, 36.490997]}, "type": "Feature", "id": "Chilchinbito", "properties": {"fips": "0412630"}}, {"geometry": {"type": "Point", "coordinates": [-109.576459, 36.150794]}, "type": "Feature", "id": "Chinle", "properties": {"fips": "0412770"}}, {"geometry": {"type": "Point", "coordinates": [-112.406064, 34.739884]}, "type": "Feature", "id": "Chino Valley", "properties": {"fips": "0412840"}}, {"geometry": {"type": "Point", "coordinates": [-114.197242, 35.409702]}, "type": "Feature", "id": "Chloride", "properties": {"fips": "0412910"}}, {"geometry": {"type": "Point", "coordinates": [-111.007141, 34.320666]}, "type": "Feature", "id": "Christopher Creek", "properties": {"fips": "0413140"}}, {"geometry": {"type": "Point", "coordinates": [-111.782192, 32.74033]}, "type": "Feature", "id": "Chuichu", "properties": {"fips": "0413190"}}, {"geometry": {"type": "Point", "coordinates": [-110.49196, 34.030367]}, "type": "Feature", "id": "Cibecue", "properties": {"fips": "0413400"}}, {"geometry": {"type": "Point", "coordinates": [-114.676294, 33.374085]}, "type": "Feature", "id": "Cibola", "properties": {"fips": "0413470"}}, {"geometry": {"type": "Point", "coordinates": [-114.215081, 34.190521]}, "type": "Feature", "id": "Cienega Springs", "properties": {"fips": "0413540"}}, {"geometry": {"type": "Point", "coordinates": [-112.439811, 33.531775]}, "type": "Feature", "id": "Citrus Park", "properties": {"fips": "0413820"}}, {"geometry": {"type": "Point", "coordinates": [-114.0723, 35.220358]}, "type": "Feature", "id": "Clacks Canyon", "properties": {"fips": "0413850"}}, {"geometry": {"type": "Point", "coordinates": [-112.058559, 34.748195]}, "type": "Feature", "id": "Clarkdale", "properties": {"fips": "0413890"}}, {"geometry": {"type": "Point", "coordinates": [-110.841873, 33.406101]}, "type": "Feature", "id": "Claypool", "properties": {"fips": "0413960"}}, {"geometry": {"type": "Point", "coordinates": [-110.304334, 34.359259]}, "type": "Feature", "id": "Clay Springs", "properties": {"fips": "0414030"}}, {"geometry": {"type": "Point", "coordinates": [-109.283987, 33.029502]}, "type": "Feature", "id": "Clifton", "properties": {"fips": "0414380"}}, {"geometry": {"type": "Point", "coordinates": [-112.985312, 36.970109]}, "type": "Feature", "id": "Colorado City", "properties": {"fips": "0414870"}}, {"geometry": {"type": "Point", "coordinates": [-111.802885, 32.053847]}, "type": "Feature", "id": "Comobabi", "properties": {"fips": "0415080"}}, {"geometry": {"type": "Point", "coordinates": [-109.614025, 34.471563]}, "type": "Feature", "id": "Concho", "properties": {"fips": "0415150"}}, {"geometry": {"type": "Point", "coordinates": [-112.865555, 34.153175]}, "type": "Feature", "id": "Congress", "properties": {"fips": "0415220"}}, {"geometry": {"type": "Point", "coordinates": [-111.527518, 32.959618]}, "type": "Feature", "id": "Coolidge", "properties": {"fips": "0415500"}}, {"geometry": {"type": "Point", "coordinates": [-110.748494, 33.433316]}, "type": "Feature", "id": "Copper Hill", "properties": {"fips": "0415600"}}, {"geometry": {"type": "Point", "coordinates": [-112.107302, 34.310276]}, "type": "Feature", "id": "Cordes Lakes", "properties": {"fips": "0415765"}}, {"geometry": {"type": "Point", "coordinates": [-109.675763, 35.651343]}, "type": "Feature", "id": "Cornfields", "properties": {"fips": "0415850"}}, {"geometry": {"type": "Point", "coordinates": [-111.908597, 34.739119]}, "type": "Feature", "id": "Cornville", "properties": {"fips": "0415920"}}, {"geometry": {"type": "Point", "coordinates": [-110.783645, 31.94948]}, "type": "Feature", "id": "Corona de Tucson", "properties": {"fips": "0416030"}}, {"geometry": {"type": "Point", "coordinates": [-109.890236, 36.072383]}, "type": "Feature", "id": "Cottonwood", "properties": {"fips": "0416360"}}, {"geometry": {"type": "Point", "coordinates": [-112.001252, 34.719747]}, "type": "Feature", "id": "Cottonwood", "properties": {"fips": "0416410"}}, {"geometry": {"type": "Point", "coordinates": [-111.987629, 31.804747]}, "type": "Feature", "id": "Cowlic", "properties": {"fips": "0416830"}}, {"geometry": {"type": "Point", "coordinates": [-113.648641, 35.422807]}, "type": "Feature", "id": "Crozier", "properties": {"fips": "0417460"}}, {"geometry": {"type": "Point", "coordinates": [-114.392634, 34.571382]}, "type": "Feature", "id": "Crystal Beach", "properties": {"fips": "0417500"}}, {"geometry": {"type": "Point", "coordinates": [-110.659327, 33.35838]}, "type": "Feature", "id": "Cutter", "properties": {"fips": "0417810"}}, {"geometry": {"type": "Point", "coordinates": [-113.541836, 32.820909]}, "type": "Feature", "id": "Dateland", "properties": {"fips": "0418160"}}, {"geometry": {"type": "Point", "coordinates": [-111.349481, 34.062342]}, "type": "Feature", "id": "Deer Creek", "properties": {"fips": "0418448"}}, {"geometry": {"type": "Point", "coordinates": [-109.434766, 36.18694]}, "type": "Feature", "id": "Del Muerto", "properties": {"fips": "0418490"}}, {"geometry": {"type": "Point", "coordinates": [-109.873758, 36.830668]}, "type": "Feature", "id": "Dennehotso", "properties": {"fips": "0418580"}}, {"geometry": {"type": "Point", "coordinates": [-114.378209, 34.546545]}, "type": "Feature", "id": "Desert Hills", "properties": {"fips": "0418740"}}, {"geometry": {"type": "Point", "coordinates": [-112.249771, 34.517439]}, "type": "Feature", "id": "Dewey-Humboldt", "properties": {"fips": "0419145"}}, {"geometry": {"type": "Point", "coordinates": [-110.306944, 35.352717]}, "type": "Feature", "id": "Dilkon", "properties": {"fips": "0419280"}}, {"geometry": {"type": "Point", "coordinates": [-114.285179, 35.590453]}, "type": "Feature", "id": "Dolan Springs", "properties": {"fips": "0419630"}}, {"geometry": {"type": "Point", "coordinates": [-111.505285, 35.268671]}, "type": "Feature", "id": "Doney Park", "properties": {"fips": "0419740"}}, {"geometry": {"type": "Point", "coordinates": [-114.678223, 32.709354]}, "type": "Feature", "id": "Donovan Estates", "properties": {"fips": "0419790"}}, {"geometry": {"type": "Point", "coordinates": [-109.541292, 31.399274]}, "type": "Feature", "id": "Douglas", "properties": {"fips": "0420050"}}, {"geometry": {"type": "Point", "coordinates": [-110.036479, 32.026362]}, "type": "Feature", "id": "Dragoon", "properties": {"fips": "0420330"}}, {"geometry": {"type": "Point", "coordinates": [-111.048816, 32.144636]}, "type": "Feature", "id": "Drexel Heights", "properties": {"fips": "0420540"}}, {"geometry": {"type": "Point", "coordinates": [-110.755088, 33.104954]}, "type": "Feature", "id": "Dripping Springs", "properties": {"fips": "0420560"}}, {"geometry": {"type": "Point", "coordinates": [-114.706782, 32.645235]}, "type": "Feature", "id": "Drysdale", "properties": {"fips": "0420570"}}, {"geometry": {"type": "Point", "coordinates": [-110.716494, 32.860011]}, "type": "Feature", "id": "Dudleyville", "properties": {"fips": "0420680"}}, {"geometry": {"type": "Point", "coordinates": [-109.0884, 32.749981]}, "type": "Feature", "id": "Duncan", "properties": {"fips": "0420750"}}, {"geometry": {"type": "Point", "coordinates": [-109.294863, 34.104946]}, "type": "Feature", "id": "Eagar", "properties": {"fips": "0420960"}}, {"geometry": {"type": "Point", "coordinates": [-109.920936, 33.8107]}, "type": "Feature", "id": "East Fork", "properties": {"fips": "0421310"}}, {"geometry": {"type": "Point", "coordinates": [-110.705266, 33.35121]}, "type": "Feature", "id": "East Globe", "properties": {"fips": "0421410"}}, {"geometry": {"type": "Point", "coordinates": [-111.364552, 34.298272]}, "type": "Feature", "id": "East Verde Estates", "properties": {"fips": "0421545"}}, {"geometry": {"type": "Point", "coordinates": [-114.483003, 33.614207]}, "type": "Feature", "id": "Ehrenberg", "properties": {"fips": "0421800"}}, {"geometry": {"type": "Point", "coordinates": [-110.783288, 33.238343]}, "type": "Feature", "id": "El Capitan", "properties": {"fips": "0421900"}}, {"geometry": {"type": "Point", "coordinates": [-110.992049, 31.765868]}, "type": "Feature", "id": "Elephant Head", "properties": {"fips": "0421980"}}, {"geometry": {"type": "Point", "coordinates": [-109.69178, 31.687563]}, "type": "Feature", "id": "Elfrida", "properties": {"fips": "0422080"}}, {"geometry": {"type": "Point", "coordinates": [-110.536105, 31.667896]}, "type": "Feature", "id": "Elgin", "properties": {"fips": "0422150"}}, {"geometry": {"type": "Point", "coordinates": [-112.327102, 33.590224]}, "type": "Feature", "id": "El Mirage", "properties": {"fips": "0422220"}}, {"geometry": {"type": "Point", "coordinates": [-111.59848, 32.743112]}, "type": "Feature", "id": "Eloy", "properties": {"fips": "0422360"}}, {"geometry": {"type": "Point", "coordinates": [-114.521481, 32.706214]}, "type": "Feature", "id": "El Prado Estates", "properties": {"fips": "0422400"}}, {"geometry": {"type": "Point", "coordinates": [-110.368892, 35.831663]}, "type": "Feature", "id": "First Mesa", "properties": {"fips": "0423512"}}, {"geometry": {"type": "Point", "coordinates": [-111.620726, 35.185217]}, "type": "Feature", "id": "Flagstaff", "properties": {"fips": "0423620"}}, {"geometry": {"type": "Point", "coordinates": [-111.412785, 33.051517]}, "type": "Feature", "id": "Florence", "properties": {"fips": "0423760"}}, {"geometry": {"type": "Point", "coordinates": [-111.334731, 34.309304]}, "type": "Feature", "id": "Flowing Springs", "properties": {"fips": "0423955"}}, {"geometry": {"type": "Point", "coordinates": [-111.00969, 32.293331]}, "type": "Feature", "id": "Flowing Wells", "properties": {"fips": "0423960"}}, {"geometry": {"type": "Point", "coordinates": [-109.988614, 33.790071]}, "type": "Feature", "id": "Fort Apache", "properties": {"fips": "0424250"}}, {"geometry": {"type": "Point", "coordinates": [-109.068504, 35.746821]}, "type": "Feature", "id": "Fort Defiance", "properties": {"fips": "0424460"}}, {"geometry": {"type": "Point", "coordinates": [-114.574849, 35.000389]}, "type": "Feature", "id": "Fort Mohave", "properties": {"fips": "0424895"}}, {"geometry": {"type": "Point", "coordinates": [-109.961258, 33.030364]}, "type": "Feature", "id": "Fort Thomas", "properties": {"fips": "0424950"}}, {"geometry": {"type": "Point", "coordinates": [-114.397523, 32.661592]}, "type": "Feature", "id": "Fortuna Foothills", "properties": {"fips": "0425030"}}, {"geometry": {"type": "Point", "coordinates": [-111.725274, 35.255416]}, "type": "Feature", "id": "Fort Valley", "properties": {"fips": "0425045"}}, {"geometry": {"type": "Point", "coordinates": [-111.737015, 33.606701]}, "type": "Feature", "id": "Fountain Hills", "properties": {"fips": "0425300"}}, {"geometry": {"type": "Point", "coordinates": [-109.072064, 32.677031]}, "type": "Feature", "id": "Franklin", "properties": {"fips": "0425650"}}, {"geometry": {"type": "Point", "coordinates": [-112.522407, 36.96666]}, "type": "Feature", "id": "Fredonia", "properties": {"fips": "0425720"}}, {"geometry": {"type": "Point", "coordinates": [-111.305152, 34.319886]}, "type": "Feature", "id": "Freedom Acres", "properties": {"fips": "0425735"}}, {"geometry": {"type": "Point", "coordinates": [-114.781096, 32.556374]}, "type": "Feature", "id": "Gadsden", "properties": {"fips": "0426070"}}, {"geometry": {"type": "Point", "coordinates": [-109.555803, 35.69177]}, "type": "Feature", "id": "Ganado", "properties": {"fips": "0426210"}}, {"geometry": {"type": "Point", "coordinates": [-111.361802, 34.369442]}, "type": "Feature", "id": "Geronimo Estates", "properties": {"fips": "0426780"}}, {"geometry": {"type": "Point", "coordinates": [-112.70553, 32.948625]}, "type": "Feature", "id": "Gila Bend", "properties": {"fips": "0427050"}}, {"geometry": {"type": "Point", "coordinates": [-112.162661, 33.273019]}, "type": "Feature", "id": "Gila Crossing", "properties": {"fips": "0427260"}}, {"geometry": {"type": "Point", "coordinates": [-111.742191, 33.310209]}, "type": "Feature", "id": "Gilbert", "properties": {"fips": "0427400"}}, {"geometry": {"type": "Point", "coordinates": [-111.288074, 34.101842]}, "type": "Feature", "id": "Gisela", "properties": {"fips": "0427540"}}, {"geometry": {"type": "Point", "coordinates": [-112.189901, 33.533111]}, "type": "Feature", "id": "Glendale", "properties": {"fips": "0427820"}}, {"geometry": {"type": "Point", "coordinates": [-110.748331, 33.390922]}, "type": "Feature", "id": "Globe", "properties": {"fips": "0428030"}}, {"geometry": {"type": "Point", "coordinates": [-111.436942, 33.371483]}, "type": "Feature", "id": "Gold Canyon", "properties": {"fips": "0428120"}}, {"geometry": {"type": "Point", "coordinates": [-114.477749, 34.781881]}, "type": "Feature", "id": "Golden Shores", "properties": {"fips": "0428190"}}, {"geometry": {"type": "Point", "coordinates": [-114.232753, 35.206066]}, "type": "Feature", "id": "Golden Valley", "properties": {"fips": "0428195"}}, {"geometry": {"type": "Point", "coordinates": [-112.366472, 33.254031]}, "type": "Feature", "id": "Goodyear", "properties": {"fips": "0428380"}}, {"geometry": {"type": "Point", "coordinates": [-111.87239, 33.197325]}, "type": "Feature", "id": "Goodyear Village", "properties": {"fips": "0428465"}}, {"geometry": {"type": "Point", "coordinates": [-112.156627, 36.049231]}, "type": "Feature", "id": "Grand Canyon Village", "properties": {"fips": "0428981"}}, {"geometry": {"type": "Point", "coordinates": [-113.804103, 36.004418]}, "type": "Feature", "id": "Grand Canyon West", "properties": {"fips": "0428985"}}, {"geometry": {"type": "Point", "coordinates": [-109.860867, 35.52864]}, "type": "Feature", "id": "Greasewood", "properties": {"fips": "0429430"}}, {"geometry": {"type": "Point", "coordinates": [-111.025471, 31.831847]}, "type": "Feature", "id": "Green Valley", "properties": {"fips": "0429710"}}, {"geometry": {"type": "Point", "coordinates": [-109.460206, 34.006577]}, "type": "Feature", "id": "Greer", "properties": {"fips": "0429850"}}, {"geometry": {"type": "Point", "coordinates": [-111.963057, 33.366362]}, "type": "Feature", "id": "Guadalupe", "properties": {"fips": "0430270"}}, {"geometry": {"type": "Point", "coordinates": [-112.023532, 31.920576]}, "type": "Feature", "id": "Gu Oidak", "properties": {"fips": "0430550"}}, {"geometry": {"type": "Point", "coordinates": [-113.725629, 35.340096]}, "type": "Feature", "id": "Hackberry", "properties": {"fips": "0430830"}}, {"geometry": {"type": "Point", "coordinates": [-110.971427, 34.219634]}, "type": "Feature", "id": "Haigler Creek", "properties": {"fips": "0430840"}}, {"geometry": {"type": "Point", "coordinates": [-111.712418, 32.005154]}, "type": "Feature", "id": "Haivana Nakya", "properties": {"fips": "0430850"}}, {"geometry": {"type": "Point", "coordinates": [-110.504049, 36.0281]}, "type": "Feature", "id": "Hard Rock", "properties": {"fips": "0431182"}}, {"geometry": {"type": "Point", "coordinates": [-110.783641, 32.998341]}, "type": "Feature", "id": "Hayden", "properties": {"fips": "0432020"}}, {"geometry": {"type": "Point", "coordinates": [-110.569561, 34.414141]}, "type": "Feature", "id": "Heber-Overgaard", "properties": {"fips": "0432310"}}, {"geometry": {"type": "Point", "coordinates": [-110.16721, 34.904624]}, "type": "Feature", "id": "Holbrook", "properties": {"fips": "0433280"}}, {"geometry": {"type": "Point", "coordinates": [-109.934385, 34.094296]}, "type": "Feature", "id": "Hondah", "properties": {"fips": "0433440"}}, {"geometry": {"type": "Point", "coordinates": [-110.639272, 35.923124]}, "type": "Feature", "id": "Hotevilla-Bacavi", "properties": {"fips": "0433945"}}, {"geometry": {"type": "Point", "coordinates": [-109.22344, 35.269308]}, "type": "Feature", "id": "Houck", "properties": {"fips": "0433980"}}, {"geometry": {"type": "Point", "coordinates": [-110.342272, 31.63079]}, "type": "Feature", "id": "Huachuca City", "properties": {"fips": "0434120"}}, {"geometry": {"type": "Point", "coordinates": [-111.017477, 34.305181]}, "type": "Feature", "id": "Hunter Creek", "properties": {"fips": "0434700"}}, {"geometry": {"type": "Point", "coordinates": [-110.801172, 33.346115]}, "type": "Feature", "id": "Icehouse Canyon", "properties": {"fips": "0434980"}}, {"geometry": {"type": "Point", "coordinates": [-110.114435, 35.409288]}, "type": "Feature", "id": "Indian Wells", "properties": {"fips": "0435310"}}, {"geometry": {"type": "Point", "coordinates": [-111.320208, 34.008248]}, "type": "Feature", "id": "Jakes Corner", "properties": {"fips": "0436010"}}, {"geometry": {"type": "Point", "coordinates": [-110.12782, 35.768199]}, "type": "Feature", "id": "Jeddito", "properties": {"fips": "0436150"}}, {"geometry": {"type": "Point", "coordinates": [-112.10726, 34.74662]}, "type": "Feature", "id": "Jerome", "properties": {"fips": "0436290"}}, {"geometry": {"type": "Point", "coordinates": [-110.329039, 34.963693]}, "type": "Feature", "id": "Joseph City", "properties": {"fips": "0436430"}}, {"geometry": {"type": "Point", "coordinates": [-111.693637, 35.092917]}, "type": "Feature", "id": "Kachina Village", "properties": {"fips": "0436475"}}, {"geometry": {"type": "Point", "coordinates": [-112.724833, 36.881003]}, "type": "Feature", "id": "Kaibab", "properties": {"fips": "0436500"}}, {"geometry": {"type": "Point", "coordinates": [-111.107135, 36.592003]}, "type": "Feature", "id": "Kaibito", "properties": {"fips": "0436640"}}, {"geometry": {"type": "Point", "coordinates": [-112.316694, 32.511375]}, "type": "Feature", "id": "Kaka", "properties": {"fips": "0436780"}}, {"geometry": {"type": "Point", "coordinates": [-114.561326, 35.22077]}, "type": "Feature", "id": "Katherine", "properties": {"fips": "0436920"}}, {"geometry": {"type": "Point", "coordinates": [-110.260486, 36.717109]}, "type": "Feature", "id": "Kayenta", "properties": {"fips": "0436990"}}, {"geometry": {"type": "Point", "coordinates": [-110.199991, 35.816972]}, "type": "Feature", "id": "Keams Canyon", "properties": {"fips": "0437130"}}, {"geometry": {"type": "Point", "coordinates": [-110.90819, 33.055967]}, "type": "Feature", "id": "Kearny", "properties": {"fips": "0437200"}}, {"geometry": {"type": "Point", "coordinates": [-114.016734, 35.216803]}, "type": "Feature", "id": "Kingman", "properties": {"fips": "0437620"}}, {"geometry": {"type": "Point", "coordinates": [-110.809745, 31.364128]}, "type": "Feature", "id": "Kino Springs", "properties": {"fips": "0437935"}}, {"geometry": {"type": "Point", "coordinates": [-109.530457, 35.499997]}, "type": "Feature", "id": "Klagetoh", "properties": {"fips": "0438250"}}, {"geometry": {"type": "Point", "coordinates": [-112.003013, 32.578281]}, "type": "Feature", "id": "Kohatk", "properties": {"fips": "0438530"}}, {"geometry": {"type": "Point", "coordinates": [-111.083855, 34.321053]}, "type": "Feature", "id": "Kohls Ranch", "properties": {"fips": "0438600"}}, {"geometry": {"type": "Point", "coordinates": [-112.16154, 33.295289]}, "type": "Feature", "id": "Komatke", "properties": {"fips": "0438655"}}, {"geometry": {"type": "Point", "coordinates": [-111.895875, 32.081502]}, "type": "Feature", "id": "Ko Vaya", "properties": {"fips": "0438940"}}, {"geometry": {"type": "Point", "coordinates": [-110.656849, 35.810245]}, "type": "Feature", "id": "Kykotsmovi Village", "properties": {"fips": "0439100"}}, {"geometry": {"type": "Point", "coordinates": [-114.314853, 34.501576]}, "type": "Feature", "id": "Lake Havasu City", "properties": {"fips": "0439370"}}, {"geometry": {"type": "Point", "coordinates": [-111.800945, 34.636908]}, "type": "Feature", "id": "Lake Montezuma", "properties": {"fips": "0439720"}}, {"geometry": {"type": "Point", "coordinates": [-109.994566, 34.152511]}, "type": "Feature", "id": "Lake of the Woods", "properties": {"fips": "0439790"}}, {"geometry": {"type": "Point", "coordinates": [-114.243285, 33.556539]}, "type": "Feature", "id": "La Paz Valley", "properties": {"fips": "0440160"}}, {"geometry": {"type": "Point", "coordinates": [-113.968463, 35.136913]}, "type": "Feature", "id": "Lazy Y U", "properties": {"fips": "0440400"}}, {"geometry": {"type": "Point", "coordinates": [-111.424438, 36.860883]}, "type": "Feature", "id": "LeChee", "properties": {"fips": "0440415"}}, {"geometry": {"type": "Point", "coordinates": [-111.003011, 35.296609]}, "type": "Feature", "id": "Leupp", "properties": {"fips": "0440630"}}, {"geometry": {"type": "Point", "coordinates": [-110.131088, 34.270838]}, "type": "Feature", "id": "Linden", "properties": {"fips": "0441085"}}, {"geometry": {"type": "Point", "coordinates": [-112.35947, 33.501761]}, "type": "Feature", "id": "Litchfield Park", "properties": {"fips": "0441330"}}, {"geometry": {"type": "Point", "coordinates": [-113.935844, 36.866265]}, "type": "Feature", "id": "Littlefield", "properties": {"fips": "0441470"}}, {"geometry": {"type": "Point", "coordinates": [-110.872812, 32.130494]}, "type": "Feature", "id": "Littletown", "properties": {"fips": "0441540"}}, {"geometry": {"type": "Point", "coordinates": [-111.785319, 33.142753]}, "type": "Feature", "id": "Lower Santan Village", "properties": {"fips": "0442460"}}, {"geometry": {"type": "Point", "coordinates": [-110.100455, 35.948058]}, "type": "Feature", "id": "Low Mountain", "properties": {"fips": "0442590"}}, {"geometry": {"type": "Point", "coordinates": [-109.226149, 36.411735]}, "type": "Feature", "id": "Lukachukai", "properties": {"fips": "0442660"}}, {"geometry": {"type": "Point", "coordinates": [-109.052822, 35.35474]}, "type": "Feature", "id": "Lupton", "properties": {"fips": "0442940"}}, {"geometry": {"type": "Point", "coordinates": [-114.089798, 35.163604]}, "type": "Feature", "id": "McConnico", "properties": {"fips": "0443150"}}, {"geometry": {"type": "Point", "coordinates": [-109.851313, 34.09226]}, "type": "Feature", "id": "McNary", "properties": {"fips": "0443430"}}, {"geometry": {"type": "Point", "coordinates": [-109.658267, 31.610078]}, "type": "Feature", "id": "McNeal", "properties": {"fips": "0443570"}}, {"geometry": {"type": "Point", "coordinates": [-112.134197, 32.170295]}, "type": "Feature", "id": "Maish Vaya", "properties": {"fips": "0443920"}}, {"geometry": {"type": "Point", "coordinates": [-110.644553, 32.72345]}, "type": "Feature", "id": "Mammoth", "properties": {"fips": "0443990"}}, {"geometry": {"type": "Point", "coordinates": [-109.637632, 36.342881]}, "type": "Feature", "id": "Many Farms", "properties": {"fips": "0444200"}}, {"geometry": {"type": "Point", "coordinates": [-111.139016, 32.465396]}, "type": "Feature", "id": "Marana", "properties": {"fips": "0444270"}}, {"geometry": {"type": "Point", "coordinates": [-112.015485, 33.045487]}, "type": "Feature", "id": "Maricopa", "properties": {"fips": "0444410"}}, {"geometry": {"type": "Point", "coordinates": [-112.227239, 33.363009]}, "type": "Feature", "id": "Maricopa Colony", "properties": {"fips": "0444450"}}, {"geometry": {"type": "Point", "coordinates": [-114.468337, 32.98642]}, "type": "Feature", "id": "Martinez Lake", "properties": {"fips": "0444830"}}, {"geometry": {"type": "Point", "coordinates": [-112.240789, 34.423365]}, "type": "Feature", "id": "Mayer", "properties": {"fips": "0445180"}}, {"geometry": {"type": "Point", "coordinates": [-111.14566, 34.347825]}, "type": "Feature", "id": "Mead Ranch", "properties": {"fips": "0445275"}}, {"geometry": {"type": "Point", "coordinates": [-114.078871, 35.953156]}, "type": "Feature", "id": "Meadview", "properties": {"fips": "0445285"}}, {"geometry": {"type": "Point", "coordinates": [-111.717379, 33.401926]}, "type": "Feature", "id": "Mesa", "properties": {"fips": "0446000"}}, {"geometry": {"type": "Point", "coordinates": [-111.295222, 34.285966]}, "type": "Feature", "id": "Mesa del Caballo", "properties": {"fips": "0446005"}}, {"geometry": {"type": "Point", "coordinates": [-110.436582, 31.96743]}, "type": "Feature", "id": "Mescal", "properties": {"fips": "0446070"}}, {"geometry": {"type": "Point", "coordinates": [-114.571385, 34.960597]}, "type": "Feature", "id": "Mesquite Creek", "properties": {"fips": "0446087"}}, {"geometry": {"type": "Point", "coordinates": [-110.872304, 33.39497]}, "type": "Feature", "id": "Miami", "properties": {"fips": "0446350"}}, {"geometry": {"type": "Point", "coordinates": [-110.148538, 31.3829]}, "type": "Feature", "id": "Miracle Valley", "properties": {"fips": "0446840"}}, {"geometry": {"type": "Point", "coordinates": [-112.754507, 36.909836]}, "type": "Feature", "id": "Moccasin", "properties": {"fips": "0447190"}}, {"geometry": {"type": "Point", "coordinates": [-111.221242, 36.112484]}, "type": "Feature", "id": "Moenkopi", "properties": {"fips": "0447330"}}, {"geometry": {"type": "Point", "coordinates": [-114.575771, 34.902433]}, "type": "Feature", "id": "Mohave Valley", "properties": {"fips": "0447400"}}, {"geometry": {"type": "Point", "coordinates": [-114.590643, 34.944901]}, "type": "Feature", "id": "Mojave Ranch Estates", "properties": {"fips": "0447495"}}, {"geometry": {"type": "Point", "coordinates": [-109.326476, 33.052197]}, "type": "Feature", "id": "Morenci", "properties": {"fips": "0447610"}}, {"geometry": {"type": "Point", "coordinates": [-112.612858, 33.855876]}, "type": "Feature", "id": "Morristown", "properties": {"fips": "0447740"}}, {"geometry": {"type": "Point", "coordinates": [-111.645195, 35.093767]}, "type": "Feature", "id": "Mountainaire", "properties": {"fips": "0447820"}}, {"geometry": {"type": "Point", "coordinates": [-111.612891, 34.919653]}, "type": "Feature", "id": "Munds Park", "properties": {"fips": "0448170"}}, {"geometry": {"type": "Point", "coordinates": [-109.927063, 31.345985]}, "type": "Feature", "id": "Naco", "properties": {"fips": "0448310"}}, {"geometry": {"type": "Point", "coordinates": [-109.476107, 35.912898]}, "type": "Feature", "id": "Nazlini", "properties": {"fips": "0449010"}}, {"geometry": {"type": "Point", "coordinates": [-111.265056, 32.430113]}, "type": "Feature", "id": "Nelson", "properties": {"fips": "0449100"}}, {"geometry": {"type": "Point", "coordinates": [-114.009081, 35.264487]}, "type": "Feature", "id": "New Kingman-Butler", "properties": {"fips": "0449270"}}, {"geometry": {"type": "Point", "coordinates": [-112.085199, 33.882498]}, "type": "Feature", "id": "New River", "properties": {"fips": "0449360"}}, {"geometry": {"type": "Point", "coordinates": [-110.933538, 31.362463]}, "type": "Feature", "id": "Nogales", "properties": {"fips": "0449640"}}, {"geometry": {"type": "Point", "coordinates": [-111.955021, 32.034183]}, "type": "Feature", "id": "Nolic", "properties": {"fips": "0449710"}}, {"geometry": {"type": "Point", "coordinates": [-109.963546, 34.001666]}, "type": "Feature", "id": "North Fork", "properties": {"fips": "0450000"}}, {"geometry": {"type": "Point", "coordinates": [-109.205912, 33.951437]}, "type": "Feature", "id": "Nutrioso", "properties": {"fips": "0450340"}}, {"geometry": {"type": "Point", "coordinates": [-109.131765, 35.476055]}, "type": "Feature", "id": "Oak Springs", "properties": {"fips": "0450480"}}, {"geometry": {"type": "Point", "coordinates": [-114.38386, 35.027375]}, "type": "Feature", "id": "Oatman", "properties": {"fips": "0450620"}}, {"geometry": {"type": "Point", "coordinates": [-110.211287, 36.98867]}, "type": "Feature", "id": "Oljato-Monument Valley", "properties": {"fips": "0451142"}}, {"geometry": {"type": "Point", "coordinates": [-110.781782, 32.609207]}, "type": "Feature", "id": "Oracle", "properties": {"fips": "0451180"}}, {"geometry": {"type": "Point", "coordinates": [-114.660588, 32.598451]}, "type": "Feature", "id": "Orange Grove Mobile Manor", "properties": {"fips": "0451465"}}, {"geometry": {"type": "Point", "coordinates": [-110.976235, 32.422094]}, "type": "Feature", "id": "Oro Valley", "properties": {"fips": "0451600"}}, {"geometry": {"type": "Point", "coordinates": [-111.343002, 34.180324]}, "type": "Feature", "id": "Oxbow Estates", "properties": {"fips": "0451775"}}, {"geometry": {"type": "Point", "coordinates": [-114.641584, 32.649591]}, "type": "Feature", "id": "Padre Ranchitos", "properties": {"fips": "0451800"}}, {"geometry": {"type": "Point", "coordinates": [-111.460867, 36.902769]}, "type": "Feature", "id": "Page", "properties": {"fips": "0451810"}}, {"geometry": {"type": "Point", "coordinates": [-110.114478, 31.387659]}, "type": "Feature", "id": "Palominas", "properties": {"fips": "0452230"}}, {"geometry": {"type": "Point", "coordinates": [-111.960845, 33.552157]}, "type": "Feature", "id": "Paradise Valley", "properties": {"fips": "0452930"}}, {"geometry": {"type": "Point", "coordinates": [-114.226423, 34.042332]}, "type": "Feature", "id": "Parker", "properties": {"fips": "0453070"}}, {"geometry": {"type": "Point", "coordinates": [-114.129654, 34.270724]}, "type": "Feature", "id": "Parker Strip", "properties": {"fips": "0453210"}}, {"geometry": {"type": "Point", "coordinates": [-111.967182, 35.285252]}, "type": "Feature", "id": "Parks", "properties": {"fips": "0453350"}}, {"geometry": {"type": "Point", "coordinates": [-110.745463, 31.544744]}, "type": "Feature", "id": "Patagonia", "properties": {"fips": "0453490"}}, {"geometry": {"type": "Point", "coordinates": [-112.493777, 34.889889]}, "type": "Feature", "id": "Paulden", "properties": {"fips": "0453560"}}, {"geometry": {"type": "Point", "coordinates": [-111.31881, 34.243905]}, "type": "Feature", "id": "Payson", "properties": {"fips": "0453700"}}, {"geometry": {"type": "Point", "coordinates": [-113.43198, 35.53145]}, "type": "Feature", "id": "Peach Springs", "properties": {"fips": "0453770"}}, {"geometry": {"type": "Point", "coordinates": [-112.765341, 34.277224]}, "type": "Feature", "id": "Peeples Valley", "properties": {"fips": "0453910"}}, {"geometry": {"type": "Point", "coordinates": [-112.3111, 33.787708]}, "type": "Feature", "id": "Peoria", "properties": {"fips": "0454050"}}, {"geometry": {"type": "Point", "coordinates": [-110.452009, 33.300961]}, "type": "Feature", "id": "Peridot", "properties": {"fips": "0454190"}}, {"geometry": {"type": "Point", "coordinates": [-112.087966, 33.572162]}, "type": "Feature", "id": "Phoenix", "properties": {"fips": "0455000"}}, {"geometry": {"type": "Point", "coordinates": [-111.494188, 32.710189]}, "type": "Feature", "id": "Picacho", "properties": {"fips": "0455210"}}, {"geometry": {"type": "Point", "coordinates": [-111.249462, 32.342663]}, "type": "Feature", "id": "Picture Rocks", "properties": {"fips": "0455300"}}, {"geometry": {"type": "Point", "coordinates": [-109.843426, 32.89308]}, "type": "Feature", "id": "Pima", "properties": {"fips": "0455560"}}, {"geometry": {"type": "Point", "coordinates": [-110.466286, 31.966573]}, "type": "Feature", "id": "Pimaco Two", "properties": {"fips": "0455575"}}, {"geometry": {"type": "Point", "coordinates": [-110.757455, 33.379854]}, "type": "Feature", "id": "Pinal", "properties": {"fips": "0455630"}}, {"geometry": {"type": "Point", "coordinates": [-111.462153, 34.381697]}, "type": "Feature", "id": "Pine", "properties": {"fips": "0455700"}}, {"geometry": {"type": "Point", "coordinates": [-110.259901, 34.320724]}, "type": "Feature", "id": "Pinedale", "properties": {"fips": "0455840"}}, {"geometry": {"type": "Point", "coordinates": [-113.873928, 35.088699]}, "type": "Feature", "id": "Pine Lake", "properties": {"fips": "0455845"}}, {"geometry": {"type": "Point", "coordinates": [-109.891036, 34.116334]}, "type": "Feature", "id": "Pinetop Country Club", "properties": {"fips": "0455880"}}, {"geometry": {"type": "Point", "coordinates": [-109.967487, 34.151486]}, "type": "Feature", "id": "Pinetop-Lakeside", "properties": {"fips": "0455980"}}, {"geometry": {"type": "Point", "coordinates": [-113.905814, 35.14663]}, "type": "Feature", "id": "Pinion Pines", "properties": {"fips": "0455983"}}, {"geometry": {"type": "Point", "coordinates": [-110.219116, 36.098856]}, "type": "Feature", "id": "Pinon", "properties": {"fips": "0456120"}}, {"geometry": {"type": "Point", "coordinates": [-109.566052, 31.360894]}, "type": "Feature", "id": "Pirtleville", "properties": {"fips": "0456400"}}, {"geometry": {"type": "Point", "coordinates": [-112.319228, 32.034917]}, "type": "Feature", "id": "Pisinemo", "properties": {"fips": "0456470"}}, {"geometry": {"type": "Point", "coordinates": [-114.404566, 33.99208]}, "type": "Feature", "id": "Poston", "properties": {"fips": "0457170"}}, {"geometry": {"type": "Point", "coordinates": [-112.448176, 34.579376]}, "type": "Feature", "id": "Prescott", "properties": {"fips": "0457380"}}, {"geometry": {"type": "Point", "coordinates": [-112.315561, 34.597689]}, "type": "Feature", "id": "Prescott Valley", "properties": {"fips": "0457450"}}, {"geometry": {"type": "Point", "coordinates": [-114.217504, 33.666976]}, "type": "Feature", "id": "Quartzsite", "properties": {"fips": "0458010"}}, {"geometry": {"type": "Point", "coordinates": [-111.640283, 33.241183]}, "type": "Feature", "id": "Queen Creek", "properties": {"fips": "0458150"}}, {"geometry": {"type": "Point", "coordinates": [-111.317862, 33.273225]}, "type": "Feature", "id": "Queen Valley", "properties": {"fips": "0458290"}}, {"geometry": {"type": "Point", "coordinates": [-109.976274, 33.873032]}, "type": "Feature", "id": "Rainbow City", "properties": {"fips": "0458620"}}, {"geometry": {"type": "Point", "coordinates": [-114.655084, 32.594385]}, "type": "Feature", "id": "Rancho Mesa Verde", "properties": {"fips": "0458870"}}, {"geometry": {"type": "Point", "coordinates": [-109.369148, 36.971624]}, "type": "Feature", "id": "Red Mesa", "properties": {"fips": "0459550"}}, {"geometry": {"type": "Point", "coordinates": [-109.064376, 36.60018]}, "type": "Feature", "id": "Red Rock", "properties": {"fips": "0459760"}}, {"geometry": {"type": "Point", "coordinates": [-111.374004, 32.561182]}, "type": "Feature", "id": "Red Rock", "properties": {"fips": "0459770"}}, {"geometry": {"type": "Point", "coordinates": [-111.154631, 32.415592]}, "type": "Feature", "id": "Rillito", "properties": {"fips": "0459900"}}, {"geometry": {"type": "Point", "coordinates": [-110.687759, 32.11207]}, "type": "Feature", "id": "Rincon Valley", "properties": {"fips": "0460120"}}, {"geometry": {"type": "Point", "coordinates": [-110.987798, 31.498168]}, "type": "Feature", "id": "Rio Rico", "properties": {"fips": "0460180"}}, {"geometry": {"type": "Point", "coordinates": [-111.673777, 33.726085]}, "type": "Feature", "id": "Rio Verde", "properties": {"fips": "0460250"}}, {"geometry": {"type": "Point", "coordinates": [-110.941078, 33.630654]}, "type": "Feature", "id": "Rock House", "properties": {"fips": "0460770"}}, {"geometry": {"type": "Point", "coordinates": [-109.619546, 36.695719]}, "type": "Feature", "id": "Rock Point", "properties": {"fips": "0460880"}}, {"geometry": {"type": "Point", "coordinates": [-111.127095, 33.657507]}, "type": "Feature", "id": "Roosevelt", "properties": {"fips": "0461300"}}, {"geometry": {"type": "Point", "coordinates": [-109.868403, 36.409489]}, "type": "Feature", "id": "Rough Rock", "properties": {"fips": "0461370"}}, {"geometry": {"type": "Point", "coordinates": [-109.463156, 36.504256]}, "type": "Feature", "id": "Round Rock", "properties": {"fips": "0461440"}}, {"geometry": {"type": "Point", "coordinates": [-111.301801, 34.187758]}, "type": "Feature", "id": "Round Valley", "properties": {"fips": "0461448"}}, {"geometry": {"type": "Point", "coordinates": [-111.354263, 34.097775]}, "type": "Feature", "id": "Rye", "properties": {"fips": "0461690"}}, {"geometry": {"type": "Point", "coordinates": [-111.981088, 33.141648]}, "type": "Feature", "id": "Sacate Village", "properties": {"fips": "0461715"}}, {"geometry": {"type": "Point", "coordinates": [-111.768246, 33.079286]}, "type": "Feature", "id": "Sacaton", "properties": {"fips": "0461720"}}, {"geometry": {"type": "Point", "coordinates": [-111.658992, 33.055897]}, "type": "Feature", "id": "Sacaton Flats Village", "properties": {"fips": "0461800"}}, {"geometry": {"type": "Point", "coordinates": [-110.855738, 32.540154]}, "type": "Feature", "id": "Saddlebrooke", "properties": {"fips": "0461940"}}, {"geometry": {"type": "Point", "coordinates": [-109.701233, 32.832106]}, "type": "Feature", "id": "Safford", "properties": {"fips": "0462000"}}, {"geometry": {"type": "Point", "coordinates": [-110.965154, 31.931894]}, "type": "Feature", "id": "Sahuarita", "properties": {"fips": "0462140"}}, {"geometry": {"type": "Point", "coordinates": [-110.221608, 31.886159]}, "type": "Feature", "id": "St. David", "properties": {"fips": "0462280"}}, {"geometry": {"type": "Point", "coordinates": [-109.376903, 34.500065]}, "type": "Feature", "id": "St. Johns", "properties": {"fips": "0462350"}}, {"geometry": {"type": "Point", "coordinates": [-112.19962, 33.314955]}, "type": "Feature", "id": "St. Johns", "properties": {"fips": "0462362"}}, {"geometry": {"type": "Point", "coordinates": [-109.096174, 35.660559]}, "type": "Feature", "id": "St. Michaels", "properties": {"fips": "0462420"}}, {"geometry": {"type": "Point", "coordinates": [-113.60605, 33.777762]}, "type": "Feature", "id": "Salome", "properties": {"fips": "0462700"}}, {"geometry": {"type": "Point", "coordinates": [-110.468, 33.349649]}, "type": "Feature", "id": "San Carlos", "properties": {"fips": "0462910"}}, {"geometry": {"type": "Point", "coordinates": [-109.322378, 35.209558]}, "type": "Feature", "id": "Sanders", "properties": {"fips": "0463050"}}, {"geometry": {"type": "Point", "coordinates": [-109.5948, 32.817963]}, "type": "Feature", "id": "San Jose", "properties": {"fips": "0463260"}}, {"geometry": {"type": "Point", "coordinates": [-114.724142, 32.486434]}, "type": "Feature", "id": "San Luis", "properties": {"fips": "0463470"}}, {"geometry": {"type": "Point", "coordinates": [-110.647113, 32.60603]}, "type": "Feature", "id": "San Manuel", "properties": {"fips": "0463540"}}, {"geometry": {"type": "Point", "coordinates": [-111.780134, 31.629493]}, "type": "Feature", "id": "San Miguel", "properties": {"fips": "0463610"}}, {"geometry": {"type": "Point", "coordinates": [-109.230993, 32.267977]}, "type": "Feature", "id": "San Simon", "properties": {"fips": "0463820"}}, {"geometry": {"type": "Point", "coordinates": [-112.159368, 33.232701]}, "type": "Feature", "id": "Santa Cruz", "properties": {"fips": "0463960"}}, {"geometry": {"type": "Point", "coordinates": [-111.547447, 33.189513]}, "type": "Feature", "id": "San Tan Valley", "properties": {"fips": "0464210"}}, {"geometry": {"type": "Point", "coordinates": [-112.046404, 32.332558]}, "type": "Feature", "id": "Santa Rosa", "properties": {"fips": "0464310"}}, {"geometry": {"type": "Point", "coordinates": [-109.157241, 35.894101]}, "type": "Feature", "id": "Sawmill", "properties": {"fips": "0464590"}}, {"geometry": {"type": "Point", "coordinates": [-114.012752, 36.793589]}, "type": "Feature", "id": "Scenic", "properties": {"fips": "0464650"}}, {"geometry": {"type": "Point", "coordinates": [-111.823682, 33.668727]}, "type": "Feature", "id": "Scottsdale", "properties": {"fips": "0465000"}}, {"geometry": {"type": "Point", "coordinates": [-110.451164, 35.479554]}, "type": "Feature", "id": "Seba Dalkai", "properties": {"fips": "0465167"}}, {"geometry": {"type": "Point", "coordinates": [-110.498343, 35.848378]}, "type": "Feature", "id": "Second Mesa", "properties": {"fips": "0465280"}}, {"geometry": {"type": "Point", "coordinates": [-111.794933, 34.857323]}, "type": "Feature", "id": "Sedona", "properties": {"fips": "0465350"}}, {"geometry": {"type": "Point", "coordinates": [-109.185521, 36.280772]}, "type": "Feature", "id": "Sehili", "properties": {"fips": "0465400"}}, {"geometry": {"type": "Point", "coordinates": [-112.857246, 35.3256]}, "type": "Feature", "id": "Seligman", "properties": {"fips": "0465420"}}, {"geometry": {"type": "Point", "coordinates": [-111.871344, 31.920885]}, "type": "Feature", "id": "Sells", "properties": {"fips": "0465490"}}, {"geometry": {"type": "Point", "coordinates": [-109.958554, 33.788181]}, "type": "Feature", "id": "Seven Mile", "properties": {"fips": "0465780"}}, {"geometry": {"type": "Point", "coordinates": [-110.535077, 35.809743]}, "type": "Feature", "id": "Shongopovi", "properties": {"fips": "0466190"}}, {"geometry": {"type": "Point", "coordinates": [-110.660459, 36.587505]}, "type": "Feature", "id": "Shonto", "properties": {"fips": "0466260"}}, {"geometry": {"type": "Point", "coordinates": [-110.031123, 34.236815]}, "type": "Feature", "id": "Show Low", "properties": {"fips": "0466470"}}, {"geometry": {"type": "Point", "coordinates": [-110.314508, 31.56541]}, "type": "Feature", "id": "Sierra Vista", "properties": {"fips": "0466820"}}, {"geometry": {"type": "Point", "coordinates": [-110.218977, 31.452512]}, "type": "Feature", "id": "Sierra Vista Southeast", "properties": {"fips": "0466845"}}, {"geometry": {"type": "Point", "coordinates": [-110.774601, 33.366782]}, "type": "Feature", "id": "Six Shooter Canyon", "properties": {"fips": "0467295"}}, {"geometry": {"type": "Point", "coordinates": [-110.089988, 34.518972]}, "type": "Feature", "id": "Snowflake", "properties": {"fips": "0467800"}}, {"geometry": {"type": "Point", "coordinates": [-114.141482, 35.252725]}, "type": "Feature", "id": "So-Hi", "properties": {"fips": "0467920"}}, {"geometry": {"type": "Point", "coordinates": [-109.628931, 32.813811]}, "type": "Feature", "id": "Solomon", "properties": {"fips": "0468010"}}, {"geometry": {"type": "Point", "coordinates": [-114.702095, 32.607768]}, "type": "Feature", "id": "Somerton", "properties": {"fips": "0468080"}}, {"geometry": {"type": "Point", "coordinates": [-110.639105, 31.66561]}, "type": "Feature", "id": "Sonoita", "properties": {"fips": "0468220"}}, {"geometry": {"type": "Point", "coordinates": [-111.774415, 31.714472]}, "type": "Feature", "id": "South Komelik", "properties": {"fips": "0468670"}}, {"geometry": {"type": "Point", "coordinates": [-110.969092, 32.195458]}, "type": "Feature", "id": "South Tucson", "properties": {"fips": "0468850"}}, {"geometry": {"type": "Point", "coordinates": [-109.29674, 34.15423]}, "type": "Feature", "id": "Springerville", "properties": {"fips": "0468990"}}, {"geometry": {"type": "Point", "coordinates": [-112.151313, 34.353089]}, "type": "Feature", "id": "Spring Valley", "properties": {"fips": "0469060"}}, {"geometry": {"type": "Point", "coordinates": [-111.962771, 32.879365]}, "type": "Feature", "id": "Stanfield", "properties": {"fips": "0469130"}}, {"geometry": {"type": "Point", "coordinates": [-111.221115, 34.254201]}, "type": "Feature", "id": "Star Valley", "properties": {"fips": "0469480"}}, {"geometry": {"type": "Point", "coordinates": [-109.850583, 35.752636]}, "type": "Feature", "id": "Steamboat", "properties": {"fips": "0469585"}}, {"geometry": {"type": "Point", "coordinates": [-111.816729, 33.152793]}, "type": "Feature", "id": "Stotonic Village", "properties": {"fips": "0469872"}}, {"geometry": {"type": "Point", "coordinates": [-111.497805, 34.403132]}, "type": "Feature", "id": "Strawberry", "properties": {"fips": "0470040"}}, {"geometry": {"type": "Point", "coordinates": [-110.7766, 32.441596]}, "type": "Feature", "id": "Summerhaven", "properties": {"fips": "0470175"}}, {"geometry": {"type": "Point", "coordinates": [-110.948759, 32.066058]}, "type": "Feature", "id": "Summit", "properties": {"fips": "0470240"}}, {"geometry": {"type": "Point", "coordinates": [-112.283108, 33.6155]}, "type": "Feature", "id": "Sun City", "properties": {"fips": "0470320"}}, {"geometry": {"type": "Point", "coordinates": [-112.357187, 33.671383]}, "type": "Feature", "id": "Sun City West", "properties": {"fips": "0470355"}}, {"geometry": {"type": "Point", "coordinates": [-109.6329, 31.884058]}, "type": "Feature", "id": "Sunizona", "properties": {"fips": "0470460"}}, {"geometry": {"type": "Point", "coordinates": [-111.869917, 33.21479]}, "type": "Feature", "id": "Sun Lakes", "properties": {"fips": "0470530"}}, {"geometry": {"type": "Point", "coordinates": [-110.031968, 34.982932]}, "type": "Feature", "id": "Sun Valley", "properties": {"fips": "0471160"}}, {"geometry": {"type": "Point", "coordinates": [-113.409131, 33.650984]}, "type": "Feature", "id": "Sunwest", "properties": {"fips": "0471220"}}, {"geometry": {"type": "Point", "coordinates": [-112.692609, 36.229964]}, "type": "Feature", "id": "Supai", "properties": {"fips": "0471230"}}, {"geometry": {"type": "Point", "coordinates": [-111.1103, 33.285146]}, "type": "Feature", "id": "Superior", "properties": {"fips": "0471300"}}, {"geometry": {"type": "Point", "coordinates": [-112.452674, 33.670612]}, "type": "Feature", "id": "Surprise", "properties": {"fips": "0471510"}}, {"geometry": {"type": "Point", "coordinates": [-111.837866, 33.12]}, "type": "Feature", "id": "Sweet Water Village", "properties": {"fips": "0471642"}}, {"geometry": {"type": "Point", "coordinates": [-109.718114, 32.727193]}, "type": "Feature", "id": "Swift Trail Junction", "properties": {"fips": "0471650"}}, {"geometry": {"type": "Point", "coordinates": [-113.961782, 32.700434]}, "type": "Feature", "id": "Tacna", "properties": {"fips": "0471790"}}, {"geometry": {"type": "Point", "coordinates": [-110.744301, 32.268412]}, "type": "Feature", "id": "Tanque Verde", "properties": {"fips": "0472000"}}, {"geometry": {"type": "Point", "coordinates": [-111.886129, 32.601195]}, "type": "Feature", "id": "Tat Momoli", "properties": {"fips": "0472280"}}, {"geometry": {"type": "Point", "coordinates": [-110.098534, 34.442748]}, "type": "Feature", "id": "Taylor", "properties": {"fips": "0472420"}}, {"geometry": {"type": "Point", "coordinates": [-109.064023, 36.933729]}, "type": "Feature", "id": "Teec Nos Pos", "properties": {"fips": "0472560"}}, {"geometry": {"type": "Point", "coordinates": [-110.405484, 35.486051]}, "type": "Feature", "id": "Tees Toh", "properties": {"fips": "0472630"}}, {"geometry": {"type": "Point", "coordinates": [-111.931782, 33.388414]}, "type": "Feature", "id": "Tempe", "properties": {"fips": "0473000"}}, {"geometry": {"type": "Point", "coordinates": [-109.743179, 32.849292]}, "type": "Feature", "id": "Thatcher", "properties": {"fips": "0473420"}}, {"geometry": {"type": "Point", "coordinates": [-112.889776, 32.918231]}, "type": "Feature", "id": "Theba", "properties": {"fips": "0473480"}}, {"geometry": {"type": "Point", "coordinates": [-111.286538, 32.059593]}, "type": "Feature", "id": "Three Points", "properties": {"fips": "0473700"}}, {"geometry": {"type": "Point", "coordinates": [-110.84315, 35.430955]}, "type": "Feature", "id": "Tolani Lake", "properties": {"fips": "0474120"}}, {"geometry": {"type": "Point", "coordinates": [-112.256184, 33.448366]}, "type": "Feature", "id": "Tolleson", "properties": {"fips": "0474190"}}, {"geometry": {"type": "Point", "coordinates": [-110.062431, 31.718474]}, "type": "Feature", "id": "Tombstone", "properties": {"fips": "0474400"}}, {"geometry": {"type": "Point", "coordinates": [-110.966665, 36.321734]}, "type": "Feature", "id": "Tonalea", "properties": {"fips": "0474470"}}, {"geometry": {"type": "Point", "coordinates": [-112.930811, 33.487986]}, "type": "Feature", "id": "Tonopah", "properties": {"fips": "0474540"}}, {"geometry": {"type": "Point", "coordinates": [-111.299724, 33.840761]}, "type": "Feature", "id": "Tonto Basin", "properties": {"fips": "0474610"}}, {"geometry": {"type": "Point", "coordinates": [-111.139313, 34.319808]}, "type": "Feature", "id": "Tonto Village", "properties": {"fips": "0474665"}}, {"geometry": {"type": "Point", "coordinates": [-111.830486, 31.807822]}, "type": "Feature", "id": "Topawa", "properties": {"fips": "0474680"}}, {"geometry": {"type": "Point", "coordinates": [-114.478792, 34.719972]}, "type": "Feature", "id": "Topock", "properties": {"fips": "0474750"}}, {"geometry": {"type": "Point", "coordinates": [-110.999724, 33.347668]}, "type": "Feature", "id": "Top-of-the-World", "properties": {"fips": "0474820"}}, {"geometry": {"type": "Point", "coordinates": [-109.938174, 35.703817]}, "type": "Feature", "id": "Toyei", "properties": {"fips": "0475310"}}, {"geometry": {"type": "Point", "coordinates": [-113.562283, 35.490676]}, "type": "Feature", "id": "Truxton", "properties": {"fips": "0475590"}}, {"geometry": {"type": "Point", "coordinates": [-109.218598, 36.303381]}, "type": "Feature", "id": "Tsaile", "properties": {"fips": "0475660"}}, {"geometry": {"type": "Point", "coordinates": [-111.057047, 31.610681]}, "type": "Feature", "id": "Tubac", "properties": {"fips": "0475940"}}, {"geometry": {"type": "Point", "coordinates": [-111.246742, 36.125013]}, "type": "Feature", "id": "Tuba City", "properties": {"fips": "0476010"}}, {"geometry": {"type": "Point", "coordinates": [-110.871062, 32.154289]}, "type": "Feature", "id": "Tucson", "properties": {"fips": "0477000"}}, {"geometry": {"type": "Point", "coordinates": [-111.125346, 32.179196]}, "type": "Feature", "id": "Tucson Estates", "properties": {"fips": "0477035"}}, {"geometry": {"type": "Point", "coordinates": [-111.047845, 31.57083]}, "type": "Feature", "id": "Tumacacori-Carmen", "properties": {"fips": "0477367"}}, {"geometry": {"type": "Point", "coordinates": [-109.9461, 33.801088]}, "type": "Feature", "id": "Turkey Creek", "properties": {"fips": "0477415"}}, {"geometry": {"type": "Point", "coordinates": [-112.143194, 35.961655]}, "type": "Feature", "id": "Tusayan", "properties": {"fips": "0477490"}}, {"geometry": {"type": "Point", "coordinates": [-111.741859, 33.115252]}, "type": "Feature", "id": "Upper Santan Village", "properties": {"fips": "0478300"}}, {"geometry": {"type": "Point", "coordinates": [-113.912864, 33.854415]}, "type": "Feature", "id": "Utting", "properties": {"fips": "0478400"}}, {"geometry": {"type": "Point", "coordinates": [-110.693807, 32.021978]}, "type": "Feature", "id": "Vail", "properties": {"fips": "0478540"}}, {"geometry": {"type": "Point", "coordinates": [-111.926902, 32.716654]}, "type": "Feature", "id": "Vaiva Vo", "properties": {"fips": "0478680"}}, {"geometry": {"type": "Point", "coordinates": [-111.111276, 32.134638]}, "type": "Feature", "id": "Valencia West", "properties": {"fips": "0478760"}}, {"geometry": {"type": "Point", "coordinates": [-113.659115, 35.38853]}, "type": "Feature", "id": "Valentine", "properties": {"fips": "0478820"}}, {"geometry": {"type": "Point", "coordinates": [-112.135121, 35.624454]}, "type": "Feature", "id": "Valle", "properties": {"fips": "0478855"}}, {"geometry": {"type": "Point", "coordinates": [-113.86271, 35.410878]}, "type": "Feature", "id": "Valle Vista", "properties": {"fips": "0478865"}}, {"geometry": {"type": "Point", "coordinates": [-112.243447, 32.468048]}, "type": "Feature", "id": "Ventana", "properties": {"fips": "0479590"}}, {"geometry": {"type": "Point", "coordinates": [-111.994041, 34.71193]}, "type": "Feature", "id": "Verde Village", "properties": {"fips": "0479830"}}, {"geometry": {"type": "Point", "coordinates": [-109.689942, 34.247901]}, "type": "Feature", "id": "Vernon", "properties": {"fips": "0479870"}}, {"geometry": {"type": "Point", "coordinates": [-113.825943, 33.727157]}, "type": "Feature", "id": "Vicksburg", "properties": {"fips": "0479940"}}, {"geometry": {"type": "Point", "coordinates": [-111.7606, 34.781269]}, "type": "Feature", "id": "Village of Oak Creek (Big Park)", "properties": {"fips": "0480095"}}, {"geometry": {"type": "Point", "coordinates": [-110.023179, 34.195823]}, "type": "Feature", "id": "Wagon Wheel", "properties": {"fips": "0480380"}}, {"geometry": {"type": "Point", "coordinates": [-112.366291, 32.174739]}, "type": "Feature", "id": "Wahak Hotrontk", "properties": {"fips": "0480430"}}, {"geometry": {"type": "Point", "coordinates": [-114.71053, 32.657296]}, "type": "Feature", "id": "Wall Lane", "properties": {"fips": "0480790"}}, {"geometry": {"type": "Point", "coordinates": [-114.126617, 35.131236]}, "type": "Feature", "id": "Walnut Creek", "properties": {"fips": "0480825"}}, {"geometry": {"type": "Point", "coordinates": [-111.271003, 34.400354]}, "type": "Feature", "id": "Washington Park", "properties": {"fips": "0481175"}}, {"geometry": {"type": "Point", "coordinates": [-114.214, 32.639995]}, "type": "Feature", "id": "Wellton", "properties": {"fips": "0481480"}}, {"geometry": {"type": "Point", "coordinates": [-114.145234, 32.623189]}, "type": "Feature", "id": "Wellton Hills", "properties": {"fips": "0481490"}}, {"geometry": {"type": "Point", "coordinates": [-113.543231, 33.832437]}, "type": "Feature", "id": "Wenden", "properties": {"fips": "0481550"}}, {"geometry": {"type": "Point", "coordinates": [-111.90045, 33.14136]}, "type": "Feature", "id": "Wet Camp Village", "properties": {"fips": "0482060"}}, {"geometry": {"type": "Point", "coordinates": [-110.816135, 33.470937]}, "type": "Feature", "id": "Wheatfields", "properties": {"fips": "0482120"}}, {"geometry": {"type": "Point", "coordinates": [-110.336365, 31.702589]}, "type": "Feature", "id": "Whetstone", "properties": {"fips": "0482155"}}, {"geometry": {"type": "Point", "coordinates": [-111.281223, 34.372721]}, "type": "Feature", "id": "Whispering Pines", "properties": {"fips": "0482270"}}, {"geometry": {"type": "Point", "coordinates": [-110.080022, 35.604666]}, "type": "Feature", "id": "Whitecone", "properties": {"fips": "0482390"}}, {"geometry": {"type": "Point", "coordinates": [-114.400368, 35.724209]}, "type": "Feature", "id": "White Hills", "properties": {"fips": "0482425"}}, {"geometry": {"type": "Point", "coordinates": [-109.986811, 34.344046]}, "type": "Feature", "id": "White Mountain Lake", "properties": {"fips": "0482450"}}, {"geometry": {"type": "Point", "coordinates": [-109.96077, 33.83976]}, "type": "Feature", "id": "Whiteriver", "properties": {"fips": "0482530"}}, {"geometry": {"type": "Point", "coordinates": [-112.730634, 32.258973]}, "type": "Feature", "id": "Why", "properties": {"fips": "0482660"}}, {"geometry": {"type": "Point", "coordinates": [-112.752672, 33.970393]}, "type": "Feature", "id": "Wickenburg", "properties": {"fips": "0482740"}}, {"geometry": {"type": "Point", "coordinates": [-109.499551, 35.417387]}, "type": "Feature", "id": "Wide Ruins", "properties": {"fips": "0482810"}}, {"geometry": {"type": "Point", "coordinates": [-113.599502, 34.693031]}, "type": "Feature", "id": "Wikieup", "properties": {"fips": "0482880"}}, {"geometry": {"type": "Point", "coordinates": [-112.615635, 34.408233]}, "type": "Feature", "id": "Wilhoit", "properties": {"fips": "0482950"}}, {"geometry": {"type": "Point", "coordinates": [-109.835734, 32.251646]}, "type": "Feature", "id": "Willcox", "properties": {"fips": "0483090"}}, {"geometry": {"type": "Point", "coordinates": [-112.183086, 35.248274]}, "type": "Feature", "id": "Williams", "properties": {"fips": "0483160"}}, {"geometry": {"type": "Point", "coordinates": [-112.534177, 34.70814]}, "type": "Feature", "id": "Williamson", "properties": {"fips": "0483388"}}, {"geometry": {"type": "Point", "coordinates": [-110.700994, 32.38814]}, "type": "Feature", "id": "Willow Canyon", "properties": {"fips": "0483475"}}, {"geometry": {"type": "Point", "coordinates": [-114.626595, 34.927669]}, "type": "Feature", "id": "Willow Valley", "properties": {"fips": "0483570"}}, {"geometry": {"type": "Point", "coordinates": [-109.063037, 35.670505]}, "type": "Feature", "id": "Window Rock", "properties": {"fips": "0483720"}}, {"geometry": {"type": "Point", "coordinates": [-110.761533, 32.98154]}, "type": "Feature", "id": "Winkelman", "properties": {"fips": "0483790"}}, {"geometry": {"type": "Point", "coordinates": [-110.709299, 35.025017]}, "type": "Feature", "id": "Winslow", "properties": {"fips": "0483930"}}, {"geometry": {"type": "Point", "coordinates": [-110.708002, 34.990905]}, "type": "Feature", "id": "Winslow West", "properties": {"fips": "0483960"}}, {"geometry": {"type": "Point", "coordinates": [-112.866536, 33.418697]}, "type": "Feature", "id": "Wintersburg", "properties": {"fips": "0484000"}}, {"geometry": {"type": "Point", "coordinates": [-112.525235, 33.775074]}, "type": "Feature", "id": "Wittmann", "properties": {"fips": "0484140"}}, {"geometry": {"type": "Point", "coordinates": [-110.03787, 34.783195]}, "type": "Feature", "id": "Woodruff", "properties": {"fips": "0484350"}}, {"geometry": {"type": "Point", "coordinates": [-112.763062, 34.228248]}, "type": "Feature", "id": "Yarnell", "properties": {"fips": "0484980"}}, {"geometry": {"type": "Point", "coordinates": [-109.19605, 32.917425]}, "type": "Feature", "id": "York", "properties": {"fips": "0485260"}}, {"geometry": {"type": "Point", "coordinates": [-110.938084, 34.124439]}, "type": "Feature", "id": "Young", "properties": {"fips": "0485330"}}, {"geometry": {"type": "Point", "coordinates": [-112.304916, 33.584969]}, "type": "Feature", "id": "Youngtown", "properties": {"fips": "0485400"}}, {"geometry": {"type": "Point", "coordinates": [-114.146145, 34.862993]}, "type": "Feature", "id": "Yucca", "properties": {"fips": "0485470"}}, {"geometry": {"type": "Point", "coordinates": [-114.521811, 32.516261]}, "type": "Feature", "id": "Yuma", "properties": {"fips": "0485540"}}]}